nojava_ipmi_kvm/__init__.py
nojava_ipmi_kvm/_version.py
nojava_ipmi_kvm/browser.py
nojava_ipmi_kvm/cli.py
nojava_ipmi_kvm/config.py
nojava_ipmi_kvm/kvm.py
nojava_ipmi_kvm/utils.py
nojava_ipmi_kvm-0.9.3.dist-info/LICENSE
nojava_ipmi_kvm-0.9.3.dist-info/METADATA
nojava_ipmi_kvm-0.9.3.dist-info/WHEEL
nojava_ipmi_kvm-0.9.3.dist-info/entry_points.txt
nojava_ipmi_kvm-0.9.3.dist-info/top_level.txt
nojava_ipmi_kvm-0.9.3.dist-info/RECORD
