Metadata-Version: 2.1
Name: nojava-ipmi-kvm
Version: 0.9.3
Summary: Access Java based ipmi kvm consoles without a local Java installation.
Home-page: https://github.com/sciapp/nojava-ipmi-kvm
Author: Ingo Meyer
Author-email: i.meyer@fz-juelich.de
License: MIT
Keywords: ipmi,kvm,vnc
Classifier: Development Status :: 4 - Beta
Classifier: Environment :: Console
Classifier: Environment :: Web Environment
Classifier: Intended Audience :: System Administrators
Classifier: License :: OSI Approved :: MIT License
Classifier: Operating System :: MacOS
Classifier: Operating System :: POSIX :: Linux
Classifier: Programming Language :: Python
Classifier: Programming Language :: Python :: 3 :: Only
Classifier: Programming Language :: Python :: 3
Classifier: Programming Language :: Python :: 3.5
Classifier: Programming Language :: Python :: 3.6
Classifier: Programming Language :: Python :: 3.7
Classifier: Topic :: System :: Systems Administration
Classifier: Topic :: Utilities
Requires-Python: ~=3.5
License-File: LICENSE
Requires-Dist: requests
Requires-Dist: yacl
Requires-Dist: pyyaml
Provides-Extra: gui
Requires-Dist: PyQt5 >=5.12 ; extra == 'gui'
Requires-Dist: PyQtWebEngine >=5.12 ; extra == 'gui'
